eos_downloader/__init__.py
eos_downloader/defaults.py
eos_downloader/tools.py
eos_downloader/cli/__init__.py
eos_downloader/cli/__main__.py
eos_downloader/cli/cli.py
eos_downloader/cli/utils.py
eos_downloader/cli/debug/__init__.py
eos_downloader/cli/debug/commands.py
eos_downloader/cli/get/__init__.py
eos_downloader/cli/get/commands.py
eos_downloader/cli/get/utils.py
eos_downloader/cli/info/__init__.py
eos_downloader/cli/info/commands.py
eos_downloader/exceptions/__init__.py
eos_downloader/helpers/__init__.py
eos_downloader/logics/__init__.py
eos_downloader/logics/arista_server.py
eos_downloader/logics/arista_xml_server.py
eos_downloader/logics/download.py
eos_downloader/models/__init__.py
eos_downloader/models/data.py
eos_downloader/models/types.py
eos_downloader/models/version.py
eos_downloader-0.13.0.dist-info/licenses/LICENSE
eos_downloader-0.13.0.dist-info/METADATA
eos_downloader-0.13.0.dist-info/WHEEL
eos_downloader-0.13.0.dist-info/entry_points.txt
eos_downloader-0.13.0.dist-info/top_level.txt
eos_downloader-0.13.0.dist-info/RECORD
