Metadata-Version: 2.4
Name: eos_downloader
Version: 0.13.0
Summary: Arista EOS/CVP downloader script
Author-email: Thomas Grimonet <thomas.grimonet@gmail.com>
Maintainer-email: Thomas Grimonet <thomas.grimonet@gmail.com>
License: Copyright (c) 2019, Arista Networks
Project-URL: Homepage, https://titom73.github.io/eos-downloader/
Project-URL: Bug Tracker, https://www.github.com/titom73/eos-downloader/issues
Project-URL: Contributing, https://www.github.com/titom73/eos-downloader
Keywords: eos_downloader,Arista,eos,cvp,network,automation,networking,devops,netdevops
Classifier: Development Status :: 4 - Beta
Classifier: Intended Audience :: Developers
Classifier: Intended Audience :: System Administrators
Classifier: Intended Audience :: Information Technology
Classifier: Topic :: System :: Software Distribution
Classifier: Topic :: Terminals
Classifier: Topic :: Utilities
Classifier: License :: OSI Approved :: Apache Software License
Classifier: Operating System :: OS Independent
Classifier: Programming Language :: Python
Classifier: Programming Language :: Python :: 3
Classifier: Programming Language :: Python :: 3.8
Classifier: Programming Language :: Python :: 3.9
Classifier: Programming Language :: Python :: 3.10
Classifier: Programming Language :: Python :: 3 :: Only
Classifier: Programming Language :: Python :: Implementation :: PyPy
Requires-Python: >=3.8
License-File: LICENSE
Requires-Dist: cryptography
Requires-Dist: paramiko
Requires-Dist: requests>=2.20.0
Requires-Dist: requests-toolbelt
Requires-Dist: scp
Requires-Dist: tqdm
Requires-Dist: loguru
Requires-Dist: rich>=13.5.2
Requires-Dist: cvprac>=1.0.7
Requires-Dist: click>=8.1.6
Requires-Dist: click-help-colors>=0.9
Requires-Dist: pydantic>2.0.0
Requires-Dist: urllib3>=2.2.2
Provides-Extra: dev
Requires-Dist: mypy<1.17,>=1.14; extra == "dev"
Requires-Dist: isort==6.0.1; extra == "dev"
Requires-Dist: mypy-extensions>=0.4.3; extra == "dev"
Requires-Dist: pre-commit>=2.20.0; extra == "dev"
Requires-Dist: pylint; extra == "dev"
Requires-Dist: pytest>=7.1.2; extra == "dev"
Requires-Dist: pytest-cov>=2.11.1; extra == "dev"
Requires-Dist: pytest-dependency; extra == "dev"
Requires-Dist: pytest-html>=3.1.1; extra == "dev"
Requires-Dist: pytest-metadata>=1.11.0; extra == "dev"
Requires-Dist: pylint-pydantic>=0.2.4; extra == "dev"
Requires-Dist: tox>=4.11; extra == "dev"
Requires-Dist: types-PyYAML; extra == "dev"
Requires-Dist: types-paramiko; extra == "dev"
Requires-Dist: types-requests; extra == "dev"
Requires-Dist: typing-extensions; extra == "dev"
Requires-Dist: yamllint; extra == "dev"
Requires-Dist: flake8>=4.0.1; extra == "dev"
Requires-Dist: pyflakes>=2.4.0; extra == "dev"
Requires-Dist: bumpver>=2023.1126; extra == "dev"
Provides-Extra: doc
Requires-Dist: fontawesome_markdown>=0.2.6; extra == "doc"
Requires-Dist: griffe>=1.2.0; extra == "doc"
Requires-Dist: mike==2.1.3; extra == "doc"
Requires-Dist: mkdocs>=1.6.1; extra == "doc"
Requires-Dist: mkdocs-autorefs>=1.2.0; extra == "doc"
Requires-Dist: mkdocs-bootswatch>=1.1; extra == "doc"
Requires-Dist: mkdocs-git-revision-date-localized-plugin>=1.2.8; extra == "doc"
Requires-Dist: mkdocs-git-revision-date-plugin>=0.3.2; extra == "doc"
Requires-Dist: mkdocs-glightbox>=0.4.0; extra == "doc"
Requires-Dist: mkdocs-material-extensions>=1.3.1; extra == "doc"
Requires-Dist: mkdocs-material>=9.5.34; extra == "doc"
Requires-Dist: mkdocstrings[python]>=0.26.0; extra == "doc"
Requires-Dist: mkdocstrings-python>=1.11.0; extra == "doc"
Requires-Dist: black>=24.10.0; extra == "doc"
Requires-Dist: mkdocs-github-admonitions-plugin; extra == "doc"
Dynamic: license-file
